{
  "sections": {
    "main": {
      "type": "main-page",
      "settings": {
      }
    },
    "16309173004eb6add0": {
      "type": "newsletter",
      "disabled": true,
      "blocks": {
        "16309173000b9a567d-0": {
          "type": "heading",
          "settings": {
            "heading": "Tudás a postafiókodban"
          }
        },
        "16309173000b9a567d-1": {
          "type": "paragraph",
          "settings": {
            "text": "<p>Számodra is fontos a folyamatos önfejlesztés? Csatlakozz, és elsőként értesítünk legfrissebb kurzusainkról, akcióinkról, ingyenes anyagainkról, online rendezvényeinkről, sőt, időnként kuponokat is találhatsz a postafiókodban.<\/p><p>Semmi spam – csak flow4learning-minőség<\/p>"
          }
        },
        "16309173000b9a567d-2": {
          "type": "email_form",
          "settings": {
          }
        }
      },
      "block_order": [
        "16309173000b9a567d-0",
        "16309173000b9a567d-1",
        "16309173000b9a567d-2"
      ],
      "settings": {
        "color_scheme": "background-2",
        "full_width": true
      }
    },
    "1657535789f5b948f2": {
      "type": "contact-form",
      "settings": {
        "heading": ""
      }
    },
    "1657702520f6074637": {
      "type": "multicolumn",
      "blocks": {
        "1657702520df83d2d2-0": {
          "type": "column",
          "settings": {
            "title": "Column",
            "text": "<p>Pair text with an image to focus on your chosen product, collection, or blog post. Add details on availability, style, or even provide a review.<\/p>",
            "column_link": ""
          }
        },
        "1657702520df83d2d2-1": {
          "type": "column",
          "settings": {
            "title": "Column",
            "text": "<p>Pair text with an image to focus on your chosen product, collection, or blog post. Add details on availability, style, or even provide a review.<\/p>",
            "column_link": ""
          }
        },
        "1657702520df83d2d2-2": {
          "type": "column",
          "settings": {
            "title": "Column",
            "text": "<p>Pair text with an image to focus on your chosen product, collection, or blog post. Add details on availability, style, or even provide a review.<\/p>",
            "column_link": ""
          }
        }
      },
      "block_order": [
        "1657702520df83d2d2-0",
        "1657702520df83d2d2-1",
        "1657702520df83d2d2-2"
      ],
      "settings": {
        "title": "Multicolumn",
        "image_width": "full",
        "image_ratio": "adapt",
        "column_alignment": "left",
        "background_style": "primary",
        "button_label": "",
        "button_link": "",
        "swipe_on_mobile": false
      }
    }
  },
  "order": [
    "main",
    "16309173004eb6add0",
    "1657535789f5b948f2",
    "1657702520f6074637"
  ]
}
